ephate/__init__.py
ephate/api.py
ephate/base.py
ephate/ephate.py
ephate/graphs.py
ephate/matrix.py
ephate/mds.py
ephate/utils.py
ephate/version.py
ephate/vne.py
EPHATE-0.1.dist-info/LICENSE.md
EPHATE-0.1.dist-info/METADATA
EPHATE-0.1.dist-info/WHEEL
EPHATE-0.1.dist-info/top_level.txt
EPHATE-0.1.dist-info/RECORD
