Metadata-Version: 2.2
Name: EPHATE
Version: 0.1
Summary: Exogenous-PHATE (E-PHATE) is a method to model the interplay of multi-dimensional, multi-modal measurements from matched samples as a low-dimensional manifold.
Home-page: https://github.com/ericabusch/EPHATE
Author: Erica Busch, Yale University
Author-email: Erica Busch <ericalindseybusch@gmail.com>
Project-URL: Homepage, https://github.com/ericabusch/EPHATE/
Project-URL: Bug Tracker, https://github.com/ericabusch/EPHATE/issues
Classifier: Programming Language :: Python :: 3
Classifier: License :: OSI Approved :: GNU General Public License (GPL)
Classifier: Operating System :: OS Independent
Requires-Python: >=3.7
License-File: LICENSE.md
Dynamic: author
Dynamic: home-page
Dynamic: requires-python
